[{"symbol": "AAPL", "name": "Apple Inc."}, {"symbol": "MSFT", "name": "Microsoft Corporation"}, {"symbol": "GOOGL", "name": "Alphabet Inc."}, {"symbol": "AMZN", "name": "Amazon.com Inc."}, {"symbol": "META", "name": "Meta Platforms Inc."}, {"symbol": "TSLA", "name": "Tesla Inc."}, {"symbol": "NVDA", "name": "NVIDIA Corporation"}, {"symbol": "JPM", "name": "JPMorgan Chase & Co."}, {"symbol": "BAC", "name": "Bank of America Corporation"}, {"symbol": "WMT", "name": "Walmart Inc."}, {"symbol": "DIS", "name": "The Walt Disney Company"}, {"symbol": "NFLX", "name": "Netflix Inc."}, {"symbol": "INTC", "name": "Intel Corporation"}, {"symbol": "AMD", "name": "Advanced Micro Devices Inc."}, {"symbol": "CSCO", "name": "Cisco Systems Inc."}, {"symbol": "IBM", "name": "International Business Machines"}, {"symbol": "GOOG", "name": "Alphabet Inc."}, {"symbol": "ADBE", "name": "Adobe Inc."}, {"symbol": "ORCL", "name": "Oracle Corporation"}, {"symbol": "UBER", "name": "Uber Technologies Inc."}, {"symbol": "PYPL", "name": "PayPal Holdings Inc."}, {"symbol": "QCOM", "name": "Qualcomm Inc."}, {"symbol": "T", "name": "AT&T Inc."}, {"symbol": "VZ", "name": "Verizon Communications Inc."}, {"symbol": "CMCSA", "name": "Comcast Corporation"}, {"symbol": "KO", "name": "The Coca-Cola Company"}, {"symbol": "PEP", "name": "PepsiCo Inc."}, {"symbol": "MCD", "name": "McDonald's Corporation"}, {"symbol": "ABT", "name": "Abbott Laboratories"}, {"symbol": "JNJ", "name": "Johnson & Johnson"}, {"symbol": "PFE", "name": "Pfizer Inc."}, {"symbol": "NKE", "name": "Nike Inc."}, {"symbol": "HD", "name": "The Home Depot Inc."}, {"symbol": "V", "name": "Visa Inc."}, {"symbol": "MA", "name": "Mastercard Incorporated"}, {"symbol": "SBUX", "name": "Starbucks Corporation"}, {"symbol": "GM", "name": "General Motors Company"}, {"symbol": "F", "name": "Ford Motor Company"}, {"symbol": "GE", "name": "General Electric Company"}, {"symbol": "BA", "name": "The Boeing Company"}, {"symbol": "CVX", "name": "Chevron Corporation"}, {"symbol": "XOM", "name": "Exxon Mobil Corporation"}, {"symbol": "GS", "name": "The Goldman Sachs Group Inc."}, {"symbol": "MS", "name": "Morgan Stanley"}, {"symbol": "TGT", "name": "Target Corporation"}, {"symbol": "COST", "name": "Costco Wholesale Corporation"}, {"symbol": "AMC", "name": "AMC Entertainment Holdings Inc."}, {"symbol": "GME", "name": "GameStop Corp."}, {"symbol": "COIN", "name": "Coinbase Global Inc."}]